async_traffic_pulse/__init__.py
async_traffic_pulse/cli.py
async_traffic_pulse/random_payload.py
async_traffic_pulse/simulate_traffic.py
async_traffic_pulse-0.0.2.dist-info/METADATA
async_traffic_pulse-0.0.2.dist-info/WHEEL
async_traffic_pulse-0.0.2.dist-info/top_level.txt
async_traffic_pulse-0.0.2.dist-info/RECORD
