Metadata-Version: 2.1
Name: async-traffic-pulse
Version: 0.0.2
Summary: A Python package for simulating HTTP traffic
Home-page: UNKNOWN
Author: Peter Bryant
Author-email: peter.bryant@gatech.edu
License: UNKNOWN
Platform: UNKNOWN
Classifier: Programming Language :: Python :: 3
Classifier: License :: OSI Approved :: MIT License
Classifier: Operating System :: OS Independent
Requires-Python: >=3.6
Requires-Dist: aiohttp ==3.8.1
Requires-Dist: Flask ==2.0.2
Requires-Dist: tqdm ==4.62.3
